src/__init__.py
src/constants.py
src/main.py
ats_friendly_resume-0.9.4.dist-info/LICENSE
ats_friendly_resume-0.9.4.dist-info/METADATA
ats_friendly_resume-0.9.4.dist-info/WHEEL
ats_friendly_resume-0.9.4.dist-info/entry_points.txt
ats_friendly_resume-0.9.4.dist-info/top_level.txt
ats_friendly_resume-0.9.4.dist-info/RECORD
