Metadata-Version: 2.2
Name: ats_friendly_resume
Version: 0.9.4
Summary: Land your interview! Optimize any PDF for seamless identification by Applicant Tracking Systems (ATS)
Home-page: https://github.com/s0d3s/ats_friendly_resume
Author: S0D3S
Classifier: Programming Language :: Python :: 3
Classifier: License :: OSI Approved :: MIT License
Classifier: Operating System :: OS Independent
Requires-Python: >=3.9
License-File: LICENSE
Requires-Dist: PyMuPDF>=1.0.0
Dynamic: author
Dynamic: classifier
Dynamic: description
Dynamic: description-content-type
Dynamic: home-page
Dynamic: requires-dist
Dynamic: requires-python
Dynamic: summary
